LICENSE
README.md
README.rst
setup.py
django_feishu_sdk/__init__.py
django_feishu_sdk/baseclient.py
django_feishu_sdk/client.py
django_feishu_sdk/decrypt.py
django_feishu_sdk/errors.py
django_feishu_sdk/settings.py
django_feishu_sdk/stores.py
django_feishu_sdk/utils.py
django_feishu_sdk.egg-info/PKG-INFO
django_feishu_sdk.egg-info/SOURCES.txt
django_feishu_sdk.egg-info/dependency_links.txt
django_feishu_sdk.egg-info/requires.txt
django_feishu_sdk.egg-info/top_level.txt
django_feishu_sdk/apis/__init__.py
django_feishu_sdk/apis/api.py
django_feishu_sdk/apis/auth.py
django_feishu_sdk/apis/base.py
django_feishu_sdk/apis/bot.py
django_feishu_sdk/apis/card.py
django_feishu_sdk/apis/cloud.py
django_feishu_sdk/apis/event.py
django_feishu_sdk/apis/message.py
django_feishu_sdk/apis/message2.py
django_feishu_sdk/models/__init__.py
django_feishu_sdk/models/bots.py
django_feishu_sdk/models/events/__init__.py
django_feishu_sdk/models/events/base.py
django_feishu_sdk/models/events/bitable.py
django_feishu_sdk/models/events/bot.py
django_feishu_sdk/models/events/contact.py
django_feishu_sdk/models/messages/__init__.py
django_feishu_sdk/models/messages/card.py
django_feishu_sdk/models/messages/message.py