Metadata-Version: 2.1
Name: django-feishu-sdk
Version: 0.2.0
Summary: A feishu api package for django
Home-page: https://gitee.com/li-pf/django_feishu_sdk
Author: lpf_andr
Author-email: lpf_andr@163.com
License: UNKNOWN
Platform: UNKNOWN
Classifier: Programming Language :: Python :: 3
Classifier: License :: OSI Approved :: MIT License
Classifier: Operating System :: OS Independent
Requires-Python: >=3.8
License-File: LICENSE
